{
	"configurations" : 
	[
		{
			"directories" : 
			[
				{
					"build" : ".",
					"jsonFile" : "directory-.-Debug-f5ebdc15457944623624.json",
					"minimumCMakeVersion" : 
					{
						"string" : "3.10"
					},
					"projectIndex" : 0,
					"source" : ".",
					"targetIndexes" : 
					[
						0
					]
				}
			],
			"name" : "Debug",
			"projects" : 
			[
				{
					"directoryIndexes" : 
					[
						0
					],
					"name" : "assn3",
					"targetIndexes" : 
					[
						0
					]
				}
			],
			"targets" : 
			[
				{
					"directoryIndex" : 0,
					"id" : "dummy_target::@6890427a1f51a3e7e1df",
					"jsonFile" : "target-dummy_target-Debug-430ed433fb3b28a71231.json",
					"name" : "dummy_target",
					"projectIndex" : 0
				}
			]
		}
	],
	"kind" : "codemodel",
	"paths" : 
	{
		"build" : "/home/lasha/paradigms/cmake-build-debug",
		"source" : "/home/lasha/paradigms"
	},
	"version" : 
	{
		"major" : 2,
		"minor" : 7
	}
}
